monkai_agent/__init__.py
monkai_agent/base.py
monkai_agent/mcp_agent.py
monkai_agent/memory.py
monkai_agent/monkai_agent_creator.py
monkai_agent/prompt_optimizer.py
monkai_agent/providers.py
monkai_agent/rate_limiter.py
monkai_agent/repl.py
monkai_agent/security.py
monkai_agent/triage_agent_creator.py
monkai_agent/types.py
monkai_agent/util.py
monkai_agent-0.1.5.dist-info/METADATA
monkai_agent-0.1.5.dist-info/WHEEL
monkai_agent-0.1.5.dist-info/RECORD
