Metadata-Version: 2.4
Name: monkai-agent
Version: 0.1.5
Summary: Core MonkAI Agent Framework
Project-URL: Homepage, https://github.com/BeMonkAI/MonkAI_agent
Project-URL: Repository, https://github.com/BeMonkAI/MonkAI_agent
Author: BeMonkAI
License: MIT
Keywords: agents,ai,framework,llm,monkai
Classifier: Development Status :: 4 - Beta
Classifier: Intended Audience :: Developers
Classifier: License :: OSI Approved :: MIT License
Classifier: Programming Language :: Python :: 3
Classifier: Programming Language :: Python :: 3.8
Classifier: Programming Language :: Python :: 3.9
Classifier: Programming Language :: Python :: 3.10
Classifier: Programming Language :: Python :: 3.11
Classifier: Topic :: Software Development :: Libraries :: Python Modules
Requires-Python: >=3.8
Requires-Dist: mcp[cli]
Requires-Dist: openai>=1.0.0
Requires-Dist: pydantic>=2.0.0
Requires-Dist: tiktoken==0.9.0
Requires-Dist: typing-extensions>=4.0.0
